LICENSE
README.md
setup.py
foldrpp/__init__.py
foldrpp/foldrpp.py
foldrpp.egg-info/PKG-INFO
foldrpp.egg-info/SOURCES.txt
foldrpp.egg-info/dependency_links.txt
foldrpp.egg-info/top_level.txt