Metadata-Version: 2.1
Name: foldrpp
Version: 0.0.2
Summary: UNKNOWN
Home-page: https://github.com/hwd404/FOLD-R-PP
Author: hwd404
Author-email: hwd404@gmail.com
License: UNKNOWN
Platform: UNKNOWN
Classifier: Programming Language :: Python :: 3
Classifier: License :: OSI Approved :: MIT License
Classifier: Operating System :: OS Independent
License-File: LICENSE
